tests
pybrightcove
