Metadata-Version: 1.0
Name: pybrightcove
Version: 1.3.7
Summary: A Python interface for the Brightcove APIs
Home-page: git://github.com/studionow/pybrightcove.git
Author: Patrick Altman
Author-email: patrick@studionow.com
License: MIT
Platform: UNKNOWN
